taskiq_aiohttp/__init__.py
taskiq_aiohttp/initializer.py
taskiq_aiohttp/py.typed
taskiq_aiohttp-0.3.1.dist-info/LICENSE
taskiq_aiohttp-0.3.1.dist-info/METADATA
taskiq_aiohttp-0.3.1.dist-info/WHEEL
taskiq_aiohttp-0.3.1.dist-info/RECORD
