Metadata-Version: 2.1
Name: taskiq-aiohttp
Version: 0.3.1
Summary: Taskiq integration with AioHTTP framework
License: LICENSE
Keywords: taskiq,tasks,distributed,async
Author: Taskiq team
Author-email: taskiq@no-reply.com
Maintainer: Taskiq team
Maintainer-email: taskiq@no-reply.com
Requires-Python: >=3.8.1,<4.0.0
Classifier: Development Status :: 3 - Alpha
Classifier: Intended Audience :: Developers
Classifier: License :: Other/Proprietary License
Classifier: Operating System :: OS Independent
Classifier: Programming Language :: Python
Classifier: Programming Language :: Python :: 3
Classifier: Programming Language :: Python :: 3.9
Classifier: Programming Language :: Python :: 3.10
Classifier: Programming Language :: Python :: 3.11
Classifier: Programming Language :: Python :: 3.12
Classifier: Programming Language :: Python :: 3 :: Only
Classifier: Programming Language :: Python :: 3.8
Classifier: Topic :: System :: Networking
Classifier: Typing :: Typed
Requires-Dist: aiohttp (>=3,<4)
Requires-Dist: taskiq (>=0.8.0,<1)
